eckmath
