Metadata-Version: 2.2
Name: eckmath
Version: 0.4.3
Summary: Um repositorio para fins academicos
Author: Guilherme Eckhardt
Author-email: eckhardt.gui@gmail.com
License: MIT License
Keywords: multmat,seglen,segintersect,point2D,point3D
License-File: LICENCE
Dynamic: author
Dynamic: author-email
Dynamic: description
Dynamic: description-content-type
Dynamic: keywords
Dynamic: license
Dynamic: summary
